computedfields/__init__.py
computedfields/admin.py
computedfields/apps.py
computedfields/graph.py
computedfields/handlers.py
computedfields/helpers.py
computedfields/models.py
computedfields/resolver.py
computedfields/settings.py
computedfields/signals.py
computedfields/thread_locals.py
computedfields/management/__init__.py
computedfields/management/commands/__init__.py
computedfields/management/commands/_helpers.py
computedfields/management/commands/checkdata.py
computedfields/management/commands/rendergraph.py
computedfields/management/commands/showdependencies.py
computedfields/management/commands/updatedata.py
computedfields/migrations/0001_initial.py
computedfields/migrations/0002_contributingmodelsmodel.py
computedfields/migrations/0003_auto_20200713_2212.py
computedfields/migrations/__init__.py
computedfields/static/computedfields/viz-lite.js
computedfields/templates/computedfields/change_list.html
computedfields/templates/computedfields/graph.html
django_computedfields-0.3.5.dist-info/licenses/LICENSE.txt
django_computedfields-0.3.5.dist-info/METADATA
django_computedfields-0.3.5.dist-info/WHEEL
django_computedfields-0.3.5.dist-info/top_level.txt
django_computedfields-0.3.5.dist-info/RECORD
