Metadata-Version: 2.4
Name: django-computedfields
Version: 0.3.5
Summary: autoupdated database fields for model methods
Home-page: https://github.com/netzkolchose/django-computedfields
Download-URL: https://github.com/netzkolchose/django-computedfields/archive/0.3.5.tar.gz
Author: netzkolchose
Author-email: j.breitbart@netzkolchose.de
License: MIT
Keywords: django,denormalization,method,decorator,autoupdate,persistent,field
Classifier: Development Status :: 4 - Beta
Classifier: Intended Audience :: Developers
Classifier: Topic :: Database
Classifier: Topic :: Database :: Front-Ends
Classifier: Topic :: Software Development :: Libraries
Classifier: Framework :: Django
Classifier: Framework :: Django :: 4.2
Classifier: Framework :: Django :: 5.1
Classifier: Framework :: Django :: 5.2
Classifier: License :: OSI Approved :: MIT License
Classifier: Programming Language :: Python :: 3.8
Classifier: Programming Language :: Python :: 3.9
Classifier: Programming Language :: Python :: 3.10
Classifier: Programming Language :: Python :: 3.11
Classifier: Programming Language :: Python :: 3.12
Classifier: Programming Language :: Python :: 3.13
License-File: LICENSE.txt
Requires-Dist: Django<6.0,>=4.2
Requires-Dist: typing_extensions>=4.1
Requires-Dist: django-fast-update
Dynamic: author
Dynamic: author-email
Dynamic: classifier
Dynamic: description
Dynamic: description-content-type
Dynamic: download-url
Dynamic: home-page
Dynamic: keywords
Dynamic: license
Dynamic: license-file
Dynamic: requires-dist
Dynamic: summary
